botrun_google_docs_reader.py
botrun_google_docs_reader-4.25.255.dist-info/METADATA
botrun_google_docs_reader-4.25.255.dist-info/WHEEL
botrun_google_docs_reader-4.25.255.dist-info/entry_points.txt
botrun_google_docs_reader-4.25.255.dist-info/RECORD
