Metadata-Version: 2.3
Name: botrun_google_docs_reader
Version: 4.25.255
Requires-Dist: google-api-python-client
Requires-Dist: google-auth
Requires-Dist: google-auth-httplib2
Requires-Dist: google-auth-oauthlib
Requires-Dist: langchain-community
Requires-Dist: litellm
Requires-Dist: python-dotenv
Requires-Dist: pytz
Requires-Dist: tavily-python
Requires-Dist: youtube-transcript-api
